CHANGELOG.md
majormode/__init__.py
majormode/xeberus/__init__.py
majormode/xeberus/service/__init__.py
majormode/xeberus/service/device/__init__.py
majormode/xeberus/service/device/db/create_device_constraint.sql
majormode/xeberus/service/device/db/create_device_index.sql
majormode/xeberus/service/device/db/create_device_table.sql
majormode/xeberus/service/device/device_service.py
majormode/xeberus/service/device/device_service_http_handler.py
majormode/xeberus/service/device/doc/api/backup/_delete_playback.rst
majormode/xeberus/service/device/doc/api/backup/_delete_venue.rst
majormode/xeberus/service/device/doc/api/backup/_get_device_activation_requests.rst
majormode/xeberus/service/device/doc/api/backup/_get_devices_locations.rst
majormode/xeberus/service/device/doc/api/backup/_get_incident.rst
majormode/xeberus/service/device/doc/api/backup/_get_vehicle_models.rst
majormode/xeberus/service/device/doc/api/backup/_get_venues.rst
majormode/xeberus/service/device/doc/api/backup/_post_device_activation.rst
majormode/xeberus/service/device/doc/api/backup/_post_device_alert_message.rst
majormode/xeberus/service/device/doc/api/backup/_post_device_allocation.rst
majormode/xeberus/service/device/doc/api/backup/_post_device_signal.rst
majormode/xeberus/service/device/doc/api/backup/_post_device_stopovers.rst
majormode/xeberus/service/device/doc/api/backup/_post_payment_cash.rst
majormode/xeberus/service/device/doc/api/backup/_post_payment_transfer.rst
majormode/xeberus/service/device/doc/api/backup/_post_playback.rst
majormode/xeberus/service/device/doc/api/backup/_post_prospect_vehicle_model_registration.rst
majormode/xeberus/service/device/doc/api/backup/_post_route.rst
majormode/xeberus/service/device/doc/api/backup/_post_sim_plan.rst
majormode/xeberus/service/device/doc/api/backup/_post_topup_card.rst
majormode/xeberus/service/device/doc/api/backup/_post_wifi_configurations.rst
majormode/xeberus/service/device/doc/api/backup/_put_device.rst
xeberus_restful_api_server_library-1.6.8.dist-info/LICENSE.md
xeberus_restful_api_server_library-1.6.8.dist-info/WHEEL
xeberus_restful_api_server_library-1.6.8.dist-info/METADATA
xeberus_restful_api_server_library-1.6.8.dist-info/RECORD
